Metadata-Version: 1.0
Name: rsherer-udacity-gaussian-distributions
Version: 0.9
Summary: Gaussian and Binomial distributions
Home-page: UNKNOWN
Author: Robert Sherer
Author-email: rsherer@gmail.com
License: UNKNOWN
Platform: UNKNOWN
